transient_in_memory_semantic_search_engine.py
transient_in_memory_semantic_search_engine-0.1.0a0.dist-info/licenses/LICENSE
transient_in_memory_semantic_search_engine-0.1.0a0.dist-info/METADATA
transient_in_memory_semantic_search_engine-0.1.0a0.dist-info/WHEEL
transient_in_memory_semantic_search_engine-0.1.0a0.dist-info/top_level.txt
transient_in_memory_semantic_search_engine-0.1.0a0.dist-info/RECORD
