Metadata-Version: 2.4
Name: transient-in-memory-semantic-search-engine
Version: 0.1.0a0
Summary: A transient, in-memory semantic search engine for small document collections, powered by sentence embeddings from an OpenAI Embeddings-compatible API.
Author-email: Jifeng Wu <jifengwu2k@gmail.com>
License-Expression: MIT
Project-URL: Homepage, https://github.com/jifengwu2k/transient-in-memory-semantic-search-engine
Project-URL: Bug Tracker, https://github.com/jifengwu2k/transient-in-memory-semantic-search-engine/issues
Classifier: Programming Language :: Python :: 2
Classifier: Programming Language :: Python :: 3
Classifier: Operating System :: OS Independent
Requires-Python: >=2
License-File: LICENSE
Requires-Dist: numpy
Requires-Dist: retrieve-sentence-embeddings
Requires-Dist: unicode-raw-input
Requires-Dist: typing; python_version < "3.5"
Dynamic: license-file
